django_db_cascade/__init__.py
django_db_cascade/deletions.py
django_db_cascade/fields.py
django_db_cascade/backends/__init__.py
django_db_cascade/backends/postgresql_psycopg2/__init__.py
django_db_cascade/backends/postgresql_psycopg2/base.py
django_db_cascade/backends/postgresql_psycopg2/schema.py
django_db_cascade_2-0.3.5.dist-info/LICENSE
django_db_cascade_2-0.3.5.dist-info/METADATA
django_db_cascade_2-0.3.5.dist-info/WHEEL
django_db_cascade_2-0.3.5.dist-info/top_level.txt
django_db_cascade_2-0.3.5.dist-info/RECORD
