Metadata-Version: 2.1
Name: django-db-cascade-2
Version: 0.3.5
Summary: Fork of django-db-cascade for Django 2.0.  Optionally use postgres db ON CASCADE DELETE on django foreign keys
Author-email: Jordan Kapelner <test@test.com>
Maintainer-email: Usama Mehmood <test2@test.com>
License: MIT
Project-URL: Homepage, http://github.com/jkapelner/django-db-cascade-2
Project-URL: Bug Tracker, http://github.com/jkapelner/django-db-cascade-2/issues
Classifier: Framework :: Django
Classifier: Topic :: Database
License-File: LICENSE
Requires-Dist: Django (>=2.0)
Requires-Dist: psycopg2 (>=2.5)
